PyRoboteq/__init__.py
PyRoboteq/roboteq_commands.py
PyRoboteq/roboteq_handler.py
PyRoboteq-0.1.2.dist-info/LICENSE
PyRoboteq-0.1.2.dist-info/METADATA
PyRoboteq-0.1.2.dist-info/WHEEL
PyRoboteq-0.1.2.dist-info/top_level.txt
PyRoboteq-0.1.2.dist-info/RECORD
