Metadata-Version: 2.1
Name: PyRoboteq
Version: 0.1.2
Summary: Python library to ease with roboteq motor driver programming
Home-page: https://github.com/Miker2808/PyRoboteq
Author: Michael Pogodin
Author-email: miker2808@gmail.com
Classifier: Programming Language :: Python :: 3
Classifier: License :: OSI Approved :: MIT License
Classifier: Operating System :: OS Independent
Requires: p
Requires: y
Requires: s
Requires: e
Requires: r
Requires: i
Requires: a
Requires: l
Requires-Python: >=3.6
License-File: LICENSE
